sysfs/__init__.py
python_sysfs-0.0.2.dist-info/LICENSE
python_sysfs-0.0.2.dist-info/METADATA
python_sysfs-0.0.2.dist-info/WHEEL
python_sysfs-0.0.2.dist-info/top_level.txt
python_sysfs-0.0.2.dist-info/RECORD
